MANIFEST.in
portal_project_view.xml
setup.py
./__init__.py
./__openerp__.py
./project.py
./tests/__init__.py
./tests/test_access_rights.py
i18n/ar.po
i18n/cs.po
i18n/de.po
i18n/es.po
i18n/fr.po
i18n/he.po
i18n/hr.po
i18n/hu.po
i18n/it.po
i18n/mk.po
i18n/nl.po
i18n/pl.po
i18n/portal_project.pot
i18n/pt.po
i18n/pt_BR.po
i18n/ro.po
i18n/sl.po
i18n/sv.po
i18n/tr.po
i18n/zh_CN.po
openerp_portal_project.egg-info/PKG-INFO
openerp_portal_project.egg-info/SOURCES.txt
openerp_portal_project.egg-info/dependency_links.txt
openerp_portal_project.egg-info/requires.txt
openerp_portal_project.egg-info/top_level.txt
security/ir.model.access.csv
security/portal_security.xml